{
  "project_info": {
    "project_number": "841467081683",
    "project_id": "manualsapp-3a589",
    "storage_bucket": "manualsapp-3a589.appspot.com"
  },
  "client": [
    {
      "client_info": {
        "mobilesdk_app_id": "1:841467081683:android:9f1a256f3007505220f526",
        "android_client_info": {
          "package_name": "com.example.user_manuals_app"
        }
      },
      "oauth_client": [],
      "api_key": [
        {
          "current_key": "AIzaSyCsIIg33yxxN0guV6ik5ofSigUYqaN28oI"
        }
      ],
      "services": {
        "appinvite_service": {
          "other_platform_oauth_client": []
        }
      }
    }
  ],
  "configuration_version": "1"
}